#pragma once
typedef enum{
    OP_AALOAD = 50,
    OP_AASTORE = 83,
    OP_ACONSTNULL = 1,
    OP_ALOAD = 25,
    OP_ALOAD0 = 42,
    OP_ALOAD1 = 43,
    OP_ALOAD2 = 44,
    OP_ALOAD3 = 45,
    OP_ANEWARRAY = 189,
    OP_ARETURN = 176,
    OP_ARRAYLENGTH = 190,
    OP_ASTORE = 58,
    OP_ASTORE0 = 75,
    OP_ASTORE1 = 76,
    OP_ASTORE2 = 77,
    OP_ASTORE3 = 78,
    OP_ATHROW = 191,
    OP_BALOAD = 51,
    OP_BASTORE = 84,
    OP_BIPUSH = 16,
    OP_CALOAD = 52,
    OP_CASTORE = 85,
    OP_CHECKCAST = 192,
    OP_D2F = 144,
    OP_D2I = 142,
    OP_D2L = 143,
    OP_DADD = 99,
    OP_DALOAD = 49,
    OP_DASTORE = 82,
    OP_DCMPG = 152,
    OP_DCMPL = 151,
    OP_DCONST0 = 14,
    OP_DCONST1 = 15,
    OP_DDIV = 111,
    OP_DLOAD = 24,
    OP_DLOAD0 = 38,
    OP_DLOAD1 = 39,
    OP_DLOAD2 = 40,
    OP_DLOAD3 = 41,
    OP_DMUL = 107,
    OP_DNEG = 119,
    OP_DREM = 115,
    OP_DRETURN = 175,
    OP_DSTORE = 57,
    OP_DSTORE0 = 71,
    OP_DSTORE1 = 72,
    OP_DSTORE2 = 73,
    OP_DSTORE3 = 74,
    OP_DSUB = 103,
    OP_DUP = 89,
    OP_DUPx1 = 90,
    OP_DUPx2 = 91,
    OP_DUP2 = 92,
    OP_DUP2x1 = 93,
    OP_DUP2x2 = 94,
    OP_F2D = 141,
    OP_F2I = 139,
    OP_F2L = 140,
    OP_FADD = 98,
    OP_FALOAD = 48,
    OP_FASTORE = 81,
    OP_FCMPG = 150,
    OP_FCMPL = 149,
    OP_FCONST0 = 11,
    OP_FCONST1 = 12,
    OP_FCONST2 = 13,
    OP_FDIV = 110,
    OP_FLOAD = 23,
    OP_FLOAD0 = 34,
    OP_FLOAD1 = 35,
    OP_FLOAD2 = 36,
    OP_FLOAD3 = 37,
    OP_FMUL = 106,
    OP_FNEG = 118,
    OP_FREM = 114,
    OP_FRETURN = 174,
    OP_FSTORE = 56,
    OP_FSTORE0 = 67,
    OP_FSTORE1 = 68,
    OP_FSTORE2 = 69,
    OP_FSTORE3 = 70,
    OP_FSUB = 102,
    OP_GETFIELD = 180,
    OP_GETSTATIC = 178,
    OP_GOTO = 167,
    OP_GOTOw = 200,
    OP_I2B = 145,
    OP_I2C = 146,
    OP_I2D = 135,
    OP_I2F = 134,
    OP_I2L = 133,
    OP_I2S = 147,
    OP_IADD = 96,
    OP_IALOAD = 46,
    OP_IAND = 126,
    OP_IASTORE = 79,
    OP_ICONSTm1 = 2,
    OP_ICONST0 = 3,
    OP_ICONST1 = 4,
    OP_ICONST2 = 5,
    OP_ICONST3 = 6,
    OP_ICONST4 = 7,
    OP_ICONST5 = 8,
    OP_IDIV = 108,
    OP_IFACMPq = 165,
    OP_IFACMPe = 166,
    OP_IFICMPeq = 159,
    OP_IFICMPne = 160,
    OP_IFICMPlt = 161,
    OP_IFICMPge = 162,
    OP_IFICMPgt = 163,
    OP_IFICMPle = 164,
    OP_IFeq = 153,
    OP_IFne = 154,
    OP_IFlt = 155,
    OP_IFge = 156,
    OP_IFgt = 157,
    OP_IFle = 158,
    OP_IFnonnull = 199,
    OP_IFnull = 198,
    OP_IINC = 132,
    OP_ILOAD = 21,
    OP_ILOAD0 = 26,
    OP_ILOAD1 = 27,
    OP_ILOAD2 = 28,
    OP_ILOAD3 = 29,
    OP_IMUL = 104,
    OP_INEG = 116,
    OP_INSTANCEOF = 193,
    OP_INVOKEDYNAMIC = 186,
    OP_INVOKEINTERFACE = 185,
    OP_INVOKESPECIAL = 183,
    OP_INVOKESTATIC = 184,
    OP_INVOKEVIRTUAL = 182,
    OP_IOR = 128,
    OP_IREM = 112,
    OP_IRETURN = 172,
    OP_ISHL = 120,
    OP_ISHR = 122,
    OP_ISTORE = 54,
    OP_ISTORE0 = 59,
    OP_ISTORE1 = 60,
    OP_ISTORE2 = 61,
    OP_ISTORE3 = 62,
    OP_ISUB = 100,
    OP_IUSHR = 124,
    OP_IXOR = 130,
    OP_JSR = 168,
    OP_JSRw = 201,
    OP_L2D = 138,
    OP_L2F = 137,
    OP_L2I = 136,
    OP_LADD = 97,
    OP_LALOAD = 47,
    OP_LAND = 127,
    OP_LASTORE = 80,
    OP_LCMP = 148,
    OP_LCONST0 = 9,
    OP_LCONST1 = 10,
    OP_LDC = 18,
    OP_LDCw = 19,
    OP_LDC2w = 20,
    OP_LDIV = 109,
    OP_LLOAD = 22,
    OP_LLOAD0 = 30,
    OP_LLOAD1 = 31,
    OP_LLOAD2 = 32,
    OP_LLOAD3 = 33,
    OP_LMUL = 105,
    OP_LNEG = 117,
    OP_LOOKUPSWITCH = 171,
    OP_LOR = 129,
    OP_LREM = 113,
    OP_LRETURN = 173,
    OP_LSHL = 121,
    OP_LSHR = 123,
    OP_LSTORE = 55,
    OP_LSTORE0 = 63,
    OP_LSTORE1 = 64,
    OP_LSTORE2 = 65,
    OP_LSTORE3 = 66,
    OP_LSUB = 101,
    OP_LUSHR = 125,
    OP_LXOR = 131,
    OP_MONITORENTER = 194,
    OP_MONITOREXIT = 195,
    OP_MULTIANEWARRAY = 197,
    OP_NEW = 187,
    OP_NEWARRAY = 188,
    OP_NOP = 0,
    OP_POP = 87,
    OP_POP2 = 88,
    OP_PUTFIELD = 181,
    OP_PUTSTATIC = 179,
    OP_RET = 169,
    OP_RETURN = 177,
    OP_SALOAD = 53,
    OP_SASTORE = 86,
    OP_SIPUSH = 17,
    OP_SWAP = 95,
    OP_TABLESWITCH = 170,
    OP_WIDE = 196,
}jvm_opcode_t;

#include "jvm_internal.h"
#include "jvm.h"
#include "class_linker.h"
#include "class_loader.h"


jvm_error_t jvm_nop_opcode(jvm_opcode_t opcode, jvm_frame_t* frame, classlinker_class_t* cur_class, unsigned nargs, void* args[]);
jvm_error_t jvm_ldc_opcode(jvm_opcode_t opcode, jvm_frame_t* frame, classlinker_class_t* cur_class, unsigned nargs, void* args[]);
jvm_error_t jvm_putstatic_opcode(jvm_opcode_t opcode, jvm_frame_t* frame, classlinker_class_t* cur_class, unsigned nargs, void* args[]);
jvm_error_t jvm_getstatic_opcode(jvm_opcode_t opcode, jvm_frame_t* frame, classlinker_class_t* cur_class, unsigned nargs, void* args[]);
jvm_error_t jvm_add_opcodes(jvm_opcode_t opcode, jvm_frame_t* frame, classlinker_class_t* cur_class, unsigned nargs, void* args[]);
jvm_error_t jvm_return_opcodes(jvm_opcode_t opcode, jvm_frame_t* frame, classlinker_class_t* cur_class, unsigned nargs, void* args[]);
jvm_error_t jvm_jsr_opcodes(jvm_opcode_t opcode, jvm_frame_t* frame, classlinker_class_t* cur_class, unsigned nargs, void* args[]);
jvm_error_t jvm_ret_opcode(jvm_opcode_t opcode, jvm_frame_t* frame, classlinker_class_t* cur_class, unsigned nargs, void* args[]);
jvm_error_t jvm_goto_opcodes(jvm_opcode_t opcode, jvm_frame_t* frame, classlinker_class_t* cur_class, unsigned nargs, void* args[]);
jvm_error_t jvm_invokestatic_opcode(jvm_opcode_t opcode, jvm_frame_t* frame, classlinker_class_t* cur_class, unsigned nargs, void* args[]);
jvm_error_t jvm_invokevirtual_opcode(jvm_opcode_t opcode, jvm_frame_t* frame, classlinker_class_t* cur_class, unsigned nargs, void* args[]);
jvm_error_t jvm_invokespecial_opcode(jvm_opcode_t opcode, jvm_frame_t* frame, classlinker_class_t* cur_class, unsigned nargs, void* args[]);
jvm_error_t jvm_pop_opcodes(jvm_opcode_t opcode, jvm_frame_t* frame, classlinker_class_t* cur_class, unsigned nargs, void* args[]);
jvm_error_t jvm_iconst_opcodes(jvm_opcode_t opcode, jvm_frame_t* frame, classlinker_class_t* cur_class, unsigned nargs, void* args[]);
jvm_error_t jvm_istore_opcodes(jvm_opcode_t opcode, jvm_frame_t* frame, classlinker_class_t* cur_class, unsigned nargs, void* args[]);
jvm_error_t jvm_iload_opcodes(jvm_opcode_t opcode, jvm_frame_t* frame, classlinker_class_t* cur_class, unsigned nargs, void* args[]);
jvm_error_t jvm_sipush_opcode(jvm_opcode_t opcode, jvm_frame_t* frame, classlinker_class_t* cur_class, unsigned nargs, void* args[]);
jvm_error_t jvm_bipush_opcode(jvm_opcode_t opcode, jvm_frame_t* frame, classlinker_class_t* cur_class, unsigned nargs, void* args[]);
jvm_error_t jvm_iinc_opcode(jvm_opcode_t opcode, jvm_frame_t* frame, classlinker_class_t* cur_class, unsigned nargs, void* args[]);
jvm_error_t jvm_ificmp_opcodes(jvm_opcode_t opcode, jvm_frame_t* frame, classlinker_class_t* cur_class, unsigned nargs, void* args[]);
jvm_error_t jvm_mul_opcodes(jvm_opcode_t opcode, jvm_frame_t* frame, classlinker_class_t* cur_class, unsigned nargs, void* args[]);
jvm_error_t jvm_add_opcodes(jvm_opcode_t opcode, jvm_frame_t* frame, classlinker_class_t* cur_class, unsigned nargs, void* args[]);
jvm_error_t jvm_new_opcode(jvm_opcode_t opcode, jvm_frame_t* frame, classlinker_class_t* cur_class, unsigned nargs, void* args[]);
jvm_error_t jvm_dup_opcodes(jvm_opcode_t opcode, jvm_frame_t* frame, classlinker_class_t* cur_class, unsigned nargs, void* args[]);
jvm_error_t jvm_astore_opcodes(jvm_opcode_t opcode, jvm_frame_t* frame, classlinker_class_t* cur_class, unsigned nargs, void* args[]);
jvm_error_t jvm_newarray_opcode(jvm_opcode_t opcode, jvm_frame_t* frame, classlinker_class_t* cur_class, unsigned nargs, void* args[]);
jvm_error_t jvm_anewarray_opcode(jvm_opcode_t opcode, jvm_frame_t* frame, classlinker_class_t* cur_class, unsigned nargs, void* args[]);
jvm_error_t jvm_aload_opcodes(jvm_opcode_t opcode, jvm_frame_t* frame, classlinker_class_t* cur_class, unsigned nargs, void* args[]);
jvm_error_t jvm_ANY2ANY_opcodes(jvm_opcode_t opcode, jvm_frame_t* frame, classlinker_class_t* cur_class, unsigned nargs, void* args[]);
jvm_error_t jvm_athrow_opcode(jvm_opcode_t opcode, jvm_frame_t* frame, classlinker_class_t* cur_class, unsigned nargs, void* args[]);
jvm_error_t jvm_getfield_opcode(jvm_opcode_t opcode, jvm_frame_t* frame, classlinker_class_t* cur_class, unsigned nargs, void* args[]);
jvm_error_t jvm_putfield_opcode(jvm_opcode_t opcode, jvm_frame_t* frame, classlinker_class_t* cur_class, unsigned nargs, void* args[]);
jvm_error_t jvm_aconstnull(jvm_opcode_t opcode, jvm_frame_t* frame, classlinker_class_t* cur_class, unsigned nargs, void* args[]);

jvm_error_t jvm_arrayload_opcode(jvm_opcode_t opcode, jvm_frame_t* frame, classlinker_class_t* cur_class, unsigned nargs, void* args[]);
jvm_error_t jvm_arraystore_opcode(jvm_opcode_t opcode, jvm_frame_t* frame, classlinker_class_t* cur_class, unsigned nargs, void* args[]);

jvm_error_t jvm_sub_opcodes(jvm_opcode_t opcode, jvm_frame_t* frame, classlinker_class_t* cur_class, unsigned nargs, void* args[]);
jvm_error_t jvm_div_opcodes(jvm_opcode_t opcode, jvm_frame_t* frame, classlinker_class_t* cur_class, unsigned nargs, void* args[]);


jvm_error_t jvm_and_opcodes(jvm_opcode_t opcode, jvm_frame_t* frame, classlinker_class_t* cur_class, unsigned nargs, void* args[]);
jvm_error_t jvm_or_opcodes(jvm_opcode_t opcode, jvm_frame_t* frame, classlinker_class_t* cur_class, unsigned nargs, void* args[]);
jvm_error_t jvm_xor_opcodes(jvm_opcode_t opcode, jvm_frame_t* frame, classlinker_class_t* cur_class, unsigned nargs, void* args[]);

jvm_error_t jvm_dcmp_opcodes(jvm_opcode_t opcode, jvm_frame_t* frame, classlinker_class_t* cur_class, unsigned nargs, void* args[]);
jvm_error_t jvm_fcmp_opcodes(jvm_opcode_t opcode, jvm_frame_t* frame, classlinker_class_t* cur_class, unsigned nargs, void* args[]);
jvm_error_t jvm_ifi_opcodes(jvm_opcode_t opcode, jvm_frame_t* frame, classlinker_class_t* cur_class, unsigned nargs, void* args[]);
jvm_error_t jvm_ifnull_opcodes(jvm_opcode_t opcode, jvm_frame_t* frame, classlinker_class_t* cur_class, unsigned nargs, void* args[]);
jvm_error_t jvm_ifacmp_opcodes(jvm_opcode_t opcode, jvm_frame_t* frame, classlinker_class_t* cur_class, unsigned nargs, void* args[]);

jvm_error_t jvm_neg_opcodes(jvm_opcode_t opcode, jvm_frame_t* frame, classlinker_class_t* cur_class, unsigned nargs, void* args[]);

jvm_error_t jvm_checkcast_opcode(jvm_opcode_t opcode, jvm_frame_t* frame, classlinker_class_t* cur_class, unsigned nargs, void* args[]);
jvm_error_t jvm_instanceof_opcode(jvm_opcode_t opcode, jvm_frame_t* frame, classlinker_class_t* cur_class, unsigned nargs, void* args[]);

jvm_error_t jvm_rem_opcodes(jvm_opcode_t opcode, jvm_frame_t* frame, classlinker_class_t* cur_class, unsigned nargs, void* args[]);

jvm_error_t jvm_shl_opcodes(jvm_opcode_t opcode, jvm_frame_t* frame, classlinker_class_t* cur_class, unsigned nargs, void* args[]);
jvm_error_t jvm_shr_opcodes(jvm_opcode_t opcode, jvm_frame_t* frame, classlinker_class_t* cur_class, unsigned nargs, void* args[]);

jvm_error_t jvm_lcmp_opcode(jvm_opcode_t opcode, jvm_frame_t* frame, classlinker_class_t* cur_class, unsigned nargs, void* args[]);

jvm_error_t jvm_lconst_opcodes(jvm_opcode_t opcode, jvm_frame_t* frame, classlinker_class_t* cur_class, unsigned nargs, void* args[]);

jvm_error_t jvm_lload_opcodes(jvm_opcode_t opcode, jvm_frame_t* frame, classlinker_class_t* cur_class, unsigned nargs, void* args[]);
jvm_error_t jvm_fload_opcodes(jvm_opcode_t opcode, jvm_frame_t* frame, classlinker_class_t* cur_class, unsigned nargs, void* args[]);
jvm_error_t jvm_dload_opcodes(jvm_opcode_t opcode, jvm_frame_t* frame, classlinker_class_t* cur_class, unsigned nargs, void* args[]);

jvm_error_t jvm_lstore_opcodes(jvm_opcode_t opcode, jvm_frame_t* frame, classlinker_class_t* cur_class, unsigned nargs, void* args[]);
jvm_error_t jvm_fstore_opcodes(jvm_opcode_t opcode, jvm_frame_t* frame, classlinker_class_t* cur_class, unsigned nargs, void* args[]);
jvm_error_t jvm_dstore_opcodes(jvm_opcode_t opcode, jvm_frame_t* frame, classlinker_class_t* cur_class, unsigned nargs, void* args[]);

jvm_error_t jvm_monitor_opcodes(jvm_opcode_t opcode, jvm_frame_t* frame, classlinker_class_t* cur_class, unsigned nargs, void* args[]);
jvm_error_t jvm_swap_opcode(jvm_opcode_t opcode, jvm_frame_t* frame, classlinker_class_t* cur_class, unsigned nargs, void* args[]);

jvm_error_t jvm_arraylength_opcode(jvm_opcode_t opcode, jvm_frame_t* frame, classlinker_class_t* cur_class, unsigned nargs, void* args[]);